day_057/src/PISO.v
`timescale 1ns / 1ps
//////////////////////////////////////////////////////////////////////////////////
// Engineer: Anjan Prasad
// Create Date: 11/17/2024 11:12:24 AM
// Module Name: PISO
//////////////////////////////////////////////////////////////////////////////////

module PISO (input load, clk, rst,
             input [7:0] data_in,
             output reg data_out);
  
  // PISO register array to load and shift data
  reg [7:0] data_reg;
  
  always @ (posedge clk or negedge rst) begin
    if (~rst)
      data_reg <= 8'h00; // Reset PISO register array on reset
    else begin
      
      // Load the data to the PISO register array and reset the serial data out register
      if (load)
      	{data_reg, data_out} <= {data_in, 1'b0};
      // Shift the loaded data 1 bit right; into the serial data out register
      else
      	{data_reg, data_out} <= {1'b0, data_reg[7:0]};
    end
  end
  
endmodule













//module PISO(
//input a,b,c,d,clk,reset,shift_load,
//output serial_out
//    );
    
//    wire Qa,Qb,Qc;
//    wire Ib,Ic,Id;
//    D_flipflop D0 (.d(a), .clk(clk), .reset(reset), .Q(Qa));
//    D_flipflop D1 (.d(Ib), .clk(clk), .reset(reset), .Q(Qb));
//    D_flipflop D2 (.d(Ic), .clk(clk), .reset(reset), .Q(Qc));
//    D_flipflop D3 (.d(Id), .clk(clk), .reset(reset), .Q(serial_out));
//    assign Ib = (Qa & shift_load) | (~shift_load & b);
//    assign Ic = (Qb & shift_load) | (~shift_load & c);
//    assign Id = (Qc & shift_load) | (~shift_load & d);
//endmodule

// Code your design here

day_057/project_1/project_1.srcs/sim_1/new/PISO_tb.v
`timescale 1ns / 1ps
//////////////////////////////////////////////////////////////////////////////////
// Engineer: Anjan Prasad
// Create Date: 11/17/2024 02:04:10 AM
// Module Name: PISO_tb
//////////////////////////////////////////////////////////////////////////////////


module PISO_tb;
  
  reg clk, rst, load;
  reg [7:0] data_in;
  
  wire data_out;
  
  PISO DUT (load, clk, rst, data_in, data_out);
  
  always #1 clk = ~clk;

  
  initial begin
    clk = 0; rst = 0; load = 0; data_in = 8'h00;
    #3 rst = 1;
    #2 load = 1; data_in = 8'd15;    
    #2 load = 0;
    #16 load = 1; data_in = 8'd255;
    #2 load = 0;
    #16 load = 1; data_in = 8'd0;
    #2 load = 0;
    #18 $stop;
    
  end
  
endmodule







//module PISO_tb;
//reg a,b,c,d,clk,reset,shift_load;
//wire serial_out;

//    PISO DUT(a,b,c,d,clk,reset,shift_load,serial_out);
    
//    initial begin
//        clk = 0;
//        forever #5 clk = ~clk; // 10 ns period
//    end

//    initial begin
//        reset = 1;
        
//        #10 a=1;b=0;c=0;d=0;reset=0 ;shift_load=0;
//        #10 a=1;b=0;c=0;d=0;reset=0 ;shift_load=1;
//        #10 a=0;b=0;c=0;d=0;reset=0 ;shift_load=0;
//        #10 a=0;b=0;c=0;d=0;reset=0 ;shift_load=1;
//        #10 a=0;b=0;c=0;d=0;reset=0 ;shift_load=0;
//        #10 a=0;b=0;c=0;d=0;reset=0 ;shift_load=1;
//        #10 a=0;b=0;c=0;d=1;reset=0 ;shift_load=0;
//        #10 a=0;b=0;c=0;d=1;reset=0 ;shift_load=1;
//        #10 a=0;b=0;c=0;d=0;reset=0 ;shift_load=0;
//        #10 a=0;b=0;c=0;d=0;reset=0 ;shift_load=0;
      
//        #50;
//        reset = 1;
//        #10 reset = 0;
//        #20 $stop;
//    end


//endmodule

day_057/project_1/project_1.sim/sim_1/behav/xsim/dump.vcd
$date
   Sun Nov  3 17:17:35 2024
$end

$version
  2024.1
  $dumpfile ("dump.vcd") 
$end

$timescale
  1ps
$end

$scope module PISO_tb $end
$var reg 1 ! clk $end
$var reg 1 " rst $end
$var reg 1 # load $end
$var reg 8 $ data_in [7:0] $end
$var wire 1 % data_out $end
$scope module DUT $end
$var wire 1 & load $end
$var wire 1 ' clk $end
$var wire 1 ( rst $end
$var wire 8 ) data_in [7:0] $end
$var reg 1 * data_out $end
$var reg 8 + data_reg [7:0] $end
$upscope $end
$upscope $end
$enddefinitions $end

#0
$dumpvars
0!
0"
0#
b0 $
x%
0&
0'
0(
b0 )
x*
b0 +
$end

#1000
1!
1'

#2000
0!
0'

#3000
1!
1"
0%
1'
1(
0*

#4000
0!
0'

#5000
1!
1#
b1111 $
1&
1'
b1111 )
b1111 +

#6000
0!
0'

#7000
1!
0#
1%
0&
1'
1*
b111 +

#8000
0!
0'

#9000
1!
1'
b11 +

#10000
0!
0'

#11000
1!
1'
b1 +

#12000
0!
0'

#13000
1!
1'
b0 +

#14000
0!
0'

#15000
1!
0%
1'
0*

#16000
0!
0'

#17000
1!
1'

#18000
0!
0'

#19000
1!
1'

#20000
0!
0'

#21000
1!
1'

#22000
0!
0'

#23000
1!
1#
b11111111 $
1&
1'
b11111111 )
b11111111 +

#24000
0!
0'

#25000
1!
0#
1%
0&
1'
1*
b1111111 +

#26000
0!
0'

#27000
1!
1'
b111111 +

#28000
0!
0'

#29000
1!
1'
b11111 +

#30000
0!
0'

#31000
1!
1'
b1111 +

#32000
0!
0'

#33000
1!
1'
b111 +

#34000
0!
0'

#35000
1!
1'
b11 +

#36000
0!
0'

#37000
1!
1'
b1 +

#38000
0!
0'

#39000
1!
1'
b0 +

#40000
0!
0'

#41000
1!
1#
b0 $
0%
1&
1'
b0 )
0*

#42000
0!
0'

#43000
1!
0#
0&
1'

