day_037/project_1/project_1.srcs/sources_1/new/decoder_5_to_32.v
`timescale 1ns / 1ps
//////////////////////////////////////////////////////////////////////////////////
// Engineer: Anjan Prasad
// Create Date: 10/28/2024 05:02:41 AM
// Module Name: decoder_5_to_32
//////////////////////////////////////////////////////////////////////////////////


module decoder_5_to_32(
  input [4:0]in,
  input enable,
  output reg [31:0]out);
  integer i;
  
  always@(*) begin
    if(enable == 1'b0)
      out = 32'd0;
    else begin
      out = 32'd1;
      for(i = 0; i < 32; i = i+1)
        begin
          case(in)
            i:out = 2**i;
          endcase
        end
    end
  end
endmodule

day_037/src/decoder_tb.v
`timescale 1ns / 1ps
//////////////////////////////////////////////////////////////////////////////////
// Engineer: Anjan Prasad
// Create Date: 10/28/2024 05:21:13 AM
// Module Name: decoder_tb
//////////////////////////////////////////////////////////////////////////////////


module decoder_tb;
  reg [4:0]in;
  reg enable;
  wire [31:0]out;
  
  
  decoder_5_to_32 DUT(in, enable, out);
  
  initial begin
    $monitor("in = %b, enable = %b, out = %b", in, enable, out);
    $dumpfile("dump.vcd"); $dumpvars;
    enable = 1'b1;
    in=32'd0;
    #5;
    	  if(out==2**in)
            $display("correct");
          else
         	$display("wrong");
    
    repeat(50) begin
      in=in+1;
      #2;
      	  if(out==2**in)
            $display("correct");
          else
         	$display("wrong");      
    end
  end
endmodule

day_037/project_1/project_1.sim/sim_1/behav/xsim/dump.vcd
$date
   Sun Oct 13 17:22:55 2024
$end

$version
  2024.1
  $dumpfile ("dump.vcd") 
$end

$timescale
  1ps
$end

$scope module decoder_tb $end
$var reg 5 ! in [4:0] $end
$var reg 1 " enable $end
$var wire 32 # out [31:0] $end
$scope module DUT $end
$var wire 5 $ in [4:0] $end
$var wire 1 % enable $end
$var reg 32 & out [31:0] $end
$var integer 32 ' i [31:0] $end
$upscope $end
$upscope $end
$enddefinitions $end

#0
$dumpvars
b0 !
1"
b1 #
b0 $
1%
b1 &
b100000 '
$end

#5000
b1 !
b10 #
b1 $
b10 &
b100000 '

#7000
b10 !
b100 #
b10 $
b100 &
b100000 '

#9000
b11 !
b1000 #
b11 $
b1000 &
b100000 '

#11000
b100 !
b10000 #
b100 $
b10000 &
b100000 '

#13000
b101 !
b100000 #
b101 $
b100000 &
b100000 '

#15000
b110 !
b1000000 #
b110 $
b1000000 &
b100000 '

#17000
b111 !
b10000000 #
b111 $
b10000000 &
b100000 '

#19000
b1000 !
b100000000 #
b1000 $
b100000000 &
b100000 '

#21000
b1001 !
b1000000000 #
b1001 $
b1000000000 &
b100000 '

#23000
b1010 !
b10000000000 #
b1010 $
b10000000000 &
b100000 '

#25000
b1011 !
b100000000000 #
b1011 $
b100000000000 &
b100000 '

#27000
b1100 !
b1000000000000 #
b1100 $
b1000000000000 &
b100000 '

#29000
b1101 !
b10000000000000 #
b1101 $
b10000000000000 &
b100000 '

#31000
b1110 !
b100000000000000 #
b1110 $
b100000000000000 &
b100000 '

#33000
b1111 !
b1000000000000000 #
b1111 $
b1000000000000000 &
b100000 '

#35000
b10000 !
b10000000000000000 #
b10000 $
b10000000000000000 &
b100000 '

#37000
b10001 !
b100000000000000000 #
b10001 $
b100000000000000000 &
b100000 '

#39000
b10010 !
b1000000000000000000 #
b10010 $
b1000000000000000000 &
b100000 '

#41000
b10011 !
b10000000000000000000 #
b10011 $
b10000000000000000000 &
b100000 '

#43000
b10100 !
b100000000000000000000 #
b10100 $
b100000000000000000000 &
b100000 '

#45000
b10101 !
b1000000000000000000000 #
b10101 $
b1000000000000000000000 &
b100000 '

#47000
b10110 !
b10000000000000000000000 #
b10110 $
b10000000000000000000000 &
b100000 '

#49000
b10111 !
b100000000000000000000000 #
b10111 $
b100000000000000000000000 &
b100000 '

#51000
b11000 !
b1000000000000000000000000 #
b11000 $
b1000000000000000000000000 &
b100000 '

#53000
b11001 !
b10000000000000000000000000 #
b11001 $
b10000000000000000000000000 &
b100000 '

#55000
b11010 !
b100000000000000000000000000 #
b11010 $
b100000000000000000000000000 &
b100000 '

#57000
b11011 !
b1000000000000000000000000000 #
b11011 $
b1000000000000000000000000000 &
b100000 '

#59000
b11100 !
b10000000000000000000000000000 #
b11100 $
b10000000000000000000000000000 &
b100000 '

#61000
b11101 !
b100000000000000000000000000000 #
b11101 $
b100000000000000000000000000000 &
b100000 '

#63000
b11110 !
b1000000000000000000000000000000 #
b11110 $
b1000000000000000000000000000000 &
b100000 '

#65000
b11111 !
b10000000000000000000000000000000 #
b11111 $
b10000000000000000000000000000000 &
b100000 '

#67000
b0 !
b1 #
b0 $
b1 &
b100000 '

#69000
b1 !
b10 #
b1 $
b10 &
b100000 '

#71000
b10 !
b100 #
b10 $
b100 &
b100000 '

#73000
b11 !
b1000 #
b11 $
b1000 &
b100000 '

#75000
b100 !
b10000 #
b100 $
b10000 &
b100000 '

#77000
b101 !
b100000 #
b101 $
b100000 &
b100000 '

#79000
b110 !
b1000000 #
b110 $
b1000000 &
b100000 '

#81000
b111 !
b10000000 #
b111 $
b10000000 &
b100000 '

#83000
b1000 !
b100000000 #
b1000 $
b100000000 &
b100000 '

#85000
b1001 !
b1000000000 #
b1001 $
b1000000000 &
b100000 '

#87000
b1010 !
b10000000000 #
b1010 $
b10000000000 &
b100000 '

#89000
b1011 !
b100000000000 #
b1011 $
b100000000000 &
b100000 '

#91000
b1100 !
b1000000000000 #
b1100 $
b1000000000000 &
b100000 '

#93000
b1101 !
b10000000000000 #
b1101 $
b10000000000000 &
b100000 '

#95000
b1110 !
b100000000000000 #
b1110 $
b100000000000000 &
b100000 '

#97000
b1111 !
b1000000000000000 #
b1111 $
b1000000000000000 &
b100000 '

#99000
b10000 !
b10000000000000000 #
b10000 $
b10000000000000000 &
b100000 '

#101000
b10001 !
b100000000000000000 #
b10001 $
b100000000000000000 &
b100000 '

#103000
b10010 !
b1000000000000000000 #
b10010 $
b1000000000000000000 &
b100000 '
